langevals_example/word_count.py
langevals_example-0.1.13.dist-info/METADATA
langevals_example-0.1.13.dist-info/WHEEL
langevals_example-0.1.13.dist-info/RECORD
