Metadata-Version: 2.4
Name: langevals-example
Version: 0.1.13
Summary: LangEvals boilerplate example evaluator for LLMs.
License: MIT
Author: Your Name
Author-email: your.email@example.com
Requires-Python: >=3.11,<4.0
Classifier: License :: OSI Approved :: MIT License
Classifier: Programming Language :: Python :: 3
Classifier: Programming Language :: Python :: 3.11
Classifier: Programming Language :: Python :: 3.12
Classifier: Programming Language :: Python :: 3.13
Classifier: Programming Language :: Python :: 3.14
Requires-Dist: langevals-core (>=0.1.18,<0.2.0)
